<?xml version="1.0" encoding="UTF-8"?>
<creaturescripts>
	<!-- Rookgaard Cockroach -->
	<event type="kill" name="TutorialCockroach" script="rookgaard/killCockroach.lua" />
	<event type="advance" name="AdvanceRookgaard" script="rookgaard/advance.lua" />
	
    <!-- The Elemental Spheres -->
	<event type="death" name="ElementalSpheres" script="quest/elemental spheres quest/the_elemental_spheres.lua"/>
	<event type="kill" name="ElementalSpheresKill" script="quest/elemental spheres quest/the_elemental_spheres.lua"/>
	<event type="login" name="ElementalSpheresLogin" script="quest/elemental spheres quest/the_elemental_spheres.lua"/>

	<!-- Gnomebase -->
	<event type="kill" name="WarzoneTwo" script="quest/gnomebase/warzone2.lua"/>
	<event type="kill" name="WarzoneThree" script="quest/gnomebase/warzone3.lua"/>
	<event type="kill" name="bossesWarzone" script="quest/gnomebase/bossesWarzone.lua"/> 
	<event type="kill" name="BigfootBurdenWiggler" script="quest/gnomebase/WigglerKill.lua" />
	
	<!-- Others -->
	<event type="login" name="PlayerLogin" script="others/login.lua"/>
	<event type="death" name="PlayerDeath" script="others/playerdeath.lua"/>
	<event type="advance" name="AdvanceSave" script="others/advance_save.lua"/>
	<event type="advance" name="Recompense" script="others/reward.lua"/>
	<event type="login" name="AddonsMounts" script="others/addons-montarias.lua"/>
	
	<event type="login" name="FirstItems" script="others/firstitems.lua" />
	<event type="login" name="RegenerateStamina" script="others/regeneratestamina.lua" />

	<event type="logout" name="PlayerLogout" script="others/logout.lua" />

	<event type="death" name="PlayerDeath" script="others/playerdeath.lua" />
	<event type="death" name="DropLoot" script="others/droploot.lua" />
	<event type="death" name="WhiteDeerDeath" script="others/whitedeer.lua" />
	<event type="death" name="WhiteDeerScoutsDeath" script="others/whitedeer_scouts.lua" />
</creaturescripts>
